[
    {
        "mob_id": 155,
        "xpos": 342.5,
        "ypos": 420.0
    },
    {
        "mob_id": 155,
        "xpos": 729.5,
        "ypos": 420.0
    },
    {
        "mob_id": 154,
        "xpos": 1164.5,
        "ypos": 266.0
    },
    {
        "mob_id": 155,
        "xpos": 1194.5,
        "ypos": 420.0
    },
    {
        "mob_id": 154,
        "xpos": 1574.0,
        "ypos": 420.0
    },
    {
        "mob_id": 154,
        "xpos": 2033.75,
        "ypos": 420.0
    },
    {
        "mob_id": 155,
        "xpos": 2372.75,
        "ypos": 420.0
    },
    {
        "mob_id": 155,
        "xpos": 2402.75,
        "ypos": 266.0
    },
    {
        "mob_id": 154,
        "xpos": 2827.25,
        "ypos": 420.0
    },
    {
        "mob_id": 155,
        "xpos": 3067.25,
        "ypos": 420.0
    },
    {
        "mob_id": 155,
        "xpos": 3454.25,
        "ypos": 420.0
    },
    {
        "mob_id": 154,
        "xpos": 3958.25,
        "ypos": 420.0
    },
    {
        "mob_id": 155,
        "xpos": 4360.0,
        "ypos": 860.0
    },
    {
        "mob_id": 155,
        "xpos": 4252.5,
        "ypos": 920.0
    },
    {
        "mob_id": 154,
        "xpos": 4065.0,
        "ypos": 920.0
    },
    {
        "mob_id": 154,
        "xpos": 3775.0,
        "ypos": 1060.0
    },
    {
        "mob_id": 155,
        "xpos": 3380.5,
        "ypos": 1060.0
    },
    {
        "mob_id": 155,
        "xpos": 3057.25,
        "ypos": 1060.0
    },
    {
        "mob_id": 155,
        "xpos": 2824.75,
        "ypos": 920.0
    },
    {
        "mob_id": 154,
        "xpos": 2659.75,
        "ypos": 920.0
    },
    {
        "mob_id": 155,
        "xpos": 2280.25,
        "ypos": 920.0
    },
    {
        "mob_id": 154,
        "xpos": 2105.0,
        "ypos": 990.0
    },
    {
        "mob_id": 154,
        "xpos": 1917.5,
        "ypos": 1060.0
    },
    {
        "mob_id": 155,
        "xpos": 1545.5,
        "ypos": 1060.0
    },
    {
        "mob_id": 155,
        "xpos": 1433.0,
        "ypos": 1060.0
    },
    {
        "mob_id": 154,
        "xpos": 1538.0,
        "ypos": 1060.0
    },
    {
        "mob_id": 155,
        "xpos": 1031.75,
        "ypos": 920.0
    },
    {
        "mob_id": 154,
        "xpos": 737.25,
        "ypos": 990.0
    },
    {
        "mob_id": 154,
        "xpos": 210.75,
        "ypos": 1060.0
    },
    {
        "mob_id": 155,
        "xpos": 1623.0,
        "ypos": 786.0
    }
]