[
    {
        "mob_id": 2,
        "xpos": 281.5,
        "ypos": 455.75
    },
    {
        "mob_id": 1,
        "xpos": 922.75,
        "ypos": 295.0
    },
    {
        "mob_id": 2,
        "xpos": 1309.0,
        "ypos": 666.5
    },
    {
        "mob_id": 2,
        "xpos": 1933.25,
        "ypos": 386.625
    },
    {
        "mob_id": 2,
        "xpos": 2640.5,
        "ypos": 912.0
    },
    {
        "mob_id": 2,
        "xpos": 3563.0,
        "ypos": 880.5
    },
    {
        "mob_id": 2,
        "xpos": 3778.0,
        "ypos": 215.0
    },
    {
        "mob_id": 1,
        "xpos": 3792.5,
        "ypos": 495.0
    },
    {
        "mob_id": 1,
        "xpos": 2801.75,
        "ypos": 715.0
    },
    {
        "mob_id": 1,
        "xpos": 2524.25,
        "ypos": 874.125
    },
    {
        "mob_id": 1,
        "xpos": 1783.5,
        "ypos": 710.0
    },
    {
        "mob_id": 1,
        "xpos": 1961.75,
        "ypos": 175.0
    }
]