[
    {
        "mob_id": 176,
        "xpos": 125.0,
        "ypos": 330.0
    },
    {
        "mob_id": 176,
        "xpos": 732.5,
        "ypos": 1025.0
    },
    {
        "mob_id": 177,
        "xpos": 1107.5,
        "ypos": 849.0
    },
    {
        "mob_id": 177,
        "xpos": 1167.5,
        "ypos": 1025.0
    },
    {
        "mob_id": 176,
        "xpos": 1529.25,
        "ypos": 1020.0
    },
    {
        "mob_id": 177,
        "xpos": 1641.75,
        "ypos": 844.0
    },
    {
        "mob_id": 177,
        "xpos": 2400.0,
        "ypos": 749.0
    },
    {
        "mob_id": 177,
        "xpos": 2832.0,
        "ypos": 925.0
    },
    {
        "mob_id": 176,
        "xpos": 3226.5,
        "ypos": 925.0
    },
    {
        "mob_id": 176,
        "xpos": 3771.0,
        "ypos": 925.0
    },
    {
        "mob_id": 177,
        "xpos": 3613.5,
        "ypos": 749.0
    },
    {
        "mob_id": 176,
        "xpos": 3136.5,
        "ypos": 749.0
    },
    {
        "mob_id": 177,
        "xpos": 2808.25,
        "ypos": 468.0
    },
    {
        "mob_id": 176,
        "xpos": 3053.5,
        "ypos": 468.0
    },
    {
        "mob_id": 177,
        "xpos": 2453.75,
        "ypos": 260.0
    }
]