[
    {
        "mob_id": 95,
        "xpos": 887.5,
        "ypos": 854.75
    },
    {
        "mob_id": 116,
        "xpos": 1574.25,
        "ypos": 1199.0
    },
    {
        "mob_id": 95,
        "xpos": 1961.25,
        "ypos": 1199.0
    },
    {
        "mob_id": 94,
        "xpos": 2355.75,
        "ypos": 1199.0
    },
    {
        "mob_id": 116,
        "xpos": 3006.0,
        "ypos": 1199.0
    },
    {
        "mob_id": 95,
        "xpos": 3400.5,
        "ypos": 1199.0
    },
    {
        "mob_id": 116,
        "xpos": 3399.0,
        "ypos": 965.0
    },
    {
        "mob_id": 94,
        "xpos": 2659.5,
        "ypos": 615.75
    },
    {
        "mob_id": 95,
        "xpos": 1927.0,
        "ypos": 765.0
    },
    {
        "mob_id": 116,
        "xpos": 1717.0,
        "ypos": 437.5
    },
    {
        "mob_id": 95,
        "xpos": 1153.0,
        "ypos": 149.0
    },
    {
        "mob_id": 115,
        "xpos": 2250.0,
        "ypos": 226.1481475830078
    },
    {
        "mob_id": 116,
        "xpos": 2253.0,
        "ypos": 225.9629669189453
    },
    {
        "mob_id": 94,
        "xpos": 2646.5,
        "ypos": 188.0
    }
]